bandsox/__init__.py
bandsox/agent.py
bandsox/cli.py
bandsox/cni.py
bandsox/core.py
bandsox/firecracker.py
bandsox/image.py
bandsox/network.py
bandsox/runner.py
bandsox/server.py
bandsox/vm.py
bandsox/static/index.html
bandsox/static/markdown_viewer.html
bandsox/static/terminal.html
bandsox/static/vm_details.html
bandsox-1.8.1.dist-info/METADATA
bandsox-1.8.1.dist-info/WHEEL
bandsox-1.8.1.dist-info/entry_points.txt
bandsox-1.8.1.dist-info/licenses/LICENSE
bandsox-1.8.1.dist-info/RECORD
