Metadata-Version: 2.4
Name: bandsox
Version: 1.8.1
Summary: Fast Firecracker microVM manager
Project-URL: Homepage, https://github.com/HACKE-RC/Bandsox/
Project-URL: Repository, https://github.com/HACKE-RC/Bandsox/
Author-email: rc <crretsim@gmail.com>
License:                                  Apache License
License-File: LICENSE
Keywords: cli,fastapi,firecracker,microvm,sandbox
Classifier: Environment :: Console
Classifier: Environment :: Web Environment
Classifier: Framework :: FastAPI
Classifier: License :: OSI Approved :: Apache Software License
Classifier: Programming Language :: Python :: 3
Classifier: Programming Language :: Python :: 3.8
Classifier: Programming Language :: Python :: 3.9
Classifier: Programming Language :: Python :: 3.10
Classifier: Programming Language :: Python :: 3.11
Requires-Python: >=3.8
Requires-Dist: fastapi
Requires-Dist: pydantic
Requires-Dist: requests
Requires-Dist: requests-unixsocket
Requires-Dist: uvicorn
Requires-Dist: websockets
